Metadata-Version: 2.4
Name: bw2iowasm
Version: 0.9.9a1
Summary: Tools for importing and export life cycle inventory databases
Author-email: Chris Mutel <cmutel@gmail.com>
Maintainer-email: Chris Mutel <cmutel@gmail.com>
Project-URL: source, https://github.com/brightway-lca/brightway2-io
Project-URL: homepage, https://github.com/brightway-lca/brightway2-io
Project-URL: tracker, https://github.com/brightway-lca/brightway2-io/issues
Classifier: Development Status :: 5 - Production/Stable
Classifier: Intended Audience :: End Users/Desktop
Classifier: Intended Audience :: Developers
Classifier: Intended Audience :: Science/Research
Classifier: License :: OSI Approved :: BSD License
Classifier: Operating System :: MacOS :: MacOS X
Classifier: Operating System :: Microsoft :: Windows
Classifier: Operating System :: POSIX
Classifier: Programming Language :: Python
Classifier: Programming Language :: Python :: 3.10
Classifier: Programming Language :: Python :: 3.11
Classifier: Programming Language :: Python :: 3.12
Classifier: Topic :: Scientific/Engineering :: Information Analysis
Classifier: Topic :: Scientific/Engineering :: Mathematics
Classifier: Topic :: Scientific/Engineering :: Visualization
Requires-Python: >=3.9
License-File: LICENSE.txt
Requires-Dist: bw2calcwasm>=2.0
Requires-Dist: bw2datawasm>=4.3
Requires-Dist: bw2parameters>=1.1.0
Requires-Dist: bw_migrations>=0.2
Requires-Dist: bw_processing>=1.0
Requires-Dist: lxml
Requires-Dist: mrio_common_metadata
Requires-Dist: numpy
Requires-Dist: openpyxl
Requires-Dist: platformdirs
Requires-Dist: pydantic
Requires-Dist: SPARQLWrapper
Requires-Dist: pyecospold
Requires-Dist: randonneur>=0.6
Requires-Dist: randonneur_data>=0.5.4
Requires-Dist: requests
Requires-Dist: scipy
Requires-Dist: stats_arrays>=0.6.5
Requires-Dist: tqdm
Requires-Dist: voluptuous
Requires-Dist: xlrd
Requires-Dist: xlsxwriter
Provides-Extra: multifunctional
Requires-Dist: bw2io; extra == "multifunctional"
Requires-Dist: multifunctional>=1.0; extra == "multifunctional"
Requires-Dist: bw_simapro_csv>=0.3.2; extra == "multifunctional"
Provides-Extra: testing
Requires-Dist: bw2io; extra == "testing"
Requires-Dist: pytest; extra == "testing"
Requires-Dist: pytest-cov; extra == "testing"
Requires-Dist: python-coveralls; extra == "testing"
Provides-Extra: dev
Requires-Dist: build; extra == "dev"
Requires-Dist: pre-commit; extra == "dev"
Requires-Dist: pylint; extra == "dev"
Requires-Dist: pytest; extra == "dev"
Requires-Dist: pytest-cov; extra == "dev"
Requires-Dist: pytest-randomly; extra == "dev"
Requires-Dist: setuptools; extra == "dev"
Dynamic: license-file
